[
    {
        "name": "Google Web - pse.google.com",
        "active": true,
        "default": true,
        "connector": "RequestsGet",
        "url": "https://www.googleapis.com/customsearch/v1",
        "query_template": "{url}?cx={cx}&key={key}&q={query_string}",
        "post_query_template": "{}",
        "http_request_headers": {},
        "page_fetch_config_json": {
            "cache": "false",
            "headers": {
                "User-Agent": "Swirlbot/1.0 (+http://swirlaiconnect.com)"
            },
            "www.businesswire.com": {
                "timeout": 60
            },
            "www.linkedin.com": {
                "timeout": 5
            },
            "rs.linkedin.com": {
                "timeout": 5
            },
            "uk.linkedin.com": {
                "timeout": 5
            },
            "au.linkedin.com": {
                "timeout": 5
            },
            "timeout": 30
        },
        "query_processors": [
            "AdaptiveQueryProcessor"
        ],
        "query_mappings": "cx=7d473806dcdde5bc6,DATE_SORT=sort=date,PAGE=start=RESULT_INDEX,NOT_CHAR=-",
        "result_processors": [
            "MappingResultProcessor",
            "DateFinderResultProcessor",
            "CosineRelevancyResultProcessor"
        ],
        "response_mappings": "FOUND=searchInformation.totalResults,RETRIEVED=queries.request[0].count,RESULTS=items",
        "result_mappings": "url=link,body=snippet,author=displayLink,cacheId,pagemap.metatags[*].['og:type'],pagemap.metatags[*].['og:site_name'],pagemap.metatags[*].['og:description'],NO_PAYLOAD",
        "credentials": "key=AIzaSyDvVeE-L6nCC9u-TTGuhggvSmzhtiTHJsA",
        "tags": [
            "Web", "WWW", "Google"
        ]
    },
    {
        "name": "Google News - news.google.com",
        "active": false,
        "default": false,
        "connector": "RequestsGet",
        "url": "https://news.google.com/rss/search",
        "query_template": "{url}?q={query_string}",
        "post_query_template": "{}",
        "http_request_headers": {},
        "query_processors": [
            "AdaptiveQueryProcessor"
        ],
        "query_mappings": "NOT_CHAR=-",
        "result_grouping_field": "",
        "result_processors": [
            "MappingResultProcessor",
            "CosineRelevancyResultProcessor"
        ],
        "response_mappings": "RESULTS=rss.channel.item",
        "result_mappings": "title=title,body=description,author=source.['#text'],date_published=pubDate,url=link,source.['@url'],NO_PAYLOAD",
        "results_per_query": 10,
        "credentials": "",
        "eval_credentials": "",
        "tags": [
            "News",
            "RSS",
            "Google"
        ]
    },
    {
        "name": "LinkedIn - www.linkedin.com",
        "active": false,
        "default": false,
        "connector": "RequestsGet",
        "url": "https://www.googleapis.com/customsearch/v1",
        "query_template": "{url}?cx={cx}&key={key}&q={query_string}+-post",
        "post_query_template": {},
        "http_request_headers": {},
        "query_processors": [
            "AdaptiveQueryProcessor"
        ],
        "query_mappings": "cx=333906f8f74144c5c,DATE_SORT=sort=date,PAGE=start=RESULT_INDEX,NOT_CHAR=-",
        "result_grouping_field": "",
        "result_processors": [
            "MappingResultProcessor",
            "RequireQueryStringInTitleResultProcessor",
            "DateFinderResultProcessor",
            "CosineRelevancyResultProcessor"
        ],
        "response_mappings": "FOUND=searchInformation.totalResults,RETRIEVED=queries.request[0].count,RESULTS=items",
        "result_mappings": "title= htmlTitle,url=link,body=snippet,cacheId,pagemap.metatags[*].['og:type'],pagemap.metatags[*].locale,pagemap.metatags[*].['og:image'],NO_PAYLOAD",
        "results_per_query": 10,
        "credentials": "key=AIzaSyDvVeE-L6nCC9u-TTGuhggvSmzhtiTHJsA",
        "eval_credentials": "",
        "tags": [
            "LinkedIn",
            "People"
        ]
    },
    {
        "name": "Swirl Documentation - docs.swirlaiconnect.com",
        "active": true,
        "default": true,
        "connector": "RequestsGet",
        "url": "https://www.googleapis.com/customsearch/v1",
        "query_template": "{url}?cx={cx}&key={key}&q={query_string}",
        "post_query_template": "{}",
        "http_request_headers": {},
        "page_fetch_config_json": {
            "cache": "false",
            "headers": {
                "User-Agent": "Swirlbot/1.0 (+http://swirlaiconnect.com)"
            },
            "www.businesswire.com": {
                "timeout": 60
            },
            "www.linkedin.com": {
                "timeout": 5
            },
            "rs.linkedin.com": {
                "timeout": 5
            },
            "uk.linkedin.com": {
                "timeout": 5
            },
            "au.linkedin.com": {
                "timeout": 5
            },
            "timeout": 30
        },
        "query_processors": [
            "AdaptiveQueryProcessor"
        ],
        "query_mappings": "cx=f047885d9696f447c,DATE_SORT=sort=date,PAGE=start=RESULT_INDEX,NOT_CHAR=-",
        "result_grouping_field": "",
        "result_processors": [
            "MappingResultProcessor",
            "DateFinderResultProcessor",
            "CosineRelevancyResultProcessor"
        ],
        "response_mappings": "FOUND=searchInformation.totalResults,RETRIEVED=queries.request[0].count,RESULTS=items",
        "result_mappings": "title=title,url=link,body=snippet,author=displayLink,cacheId,pagemap.metatags[*].['og:type'],pagemap.metatags[*].['og:site_name'],pagemap.metatags[*].['og:description'],NO_PAYLOAD",
        "results_per_query": 10,
        "credentials": "key=AIzaSyDvVeE-L6nCC9u-TTGuhggvSmzhtiTHJsA",
        "eval_credentials": "",
        "tags": [
            "Swirl",
            "Dev"
        ]
    }
]
