{
    "name": "M365 OneDrive",
    "active": true,
    "default": true,
    "connector": "M365OneDrive",
    "url": "",
    "query_template": "{url}",
    "query_processor": "",
    "query_processors": [
        "AdaptiveQueryProcessor"
    ],
    "query_mappings": "NOT=true,NOT_CHAR=-",
    "result_processor": "",
    "result_processors": [
        "MappingResultProcessor"
    ],
    "response_mappings": "",
    "result_mappings": "title=resource.name,body='{resource.name} - {summary}',date_published=resource.createdDateTime,url=resource.webUrl,author=resource.createdBy.user.displayName,resource.lastModifiedBy.user.displayName,resource.lastModifiedDateTime,FILE_SYSTEM,NO_PAYLOAD",
    "results_per_query": 10,
    "credentials": "",
    "eval_credentials": "",
    "tags": [
        "Microsoft",
        "OneDrive"
    ]
}